{"cameraMode":{"drawMode":0,"name":"Shaded","section":"Shading Mode"},"sceneLighting":true,"audioPlay":false,"sceneViewState":{"m_AlwaysRefresh":false,"showFog":true,"showSkybox":true,"showFlares":true,"showImageEffects":true,"showParticleSystems":true,"showVisualEffectGraphs":true,"m_FxEnabled":true},"in2DMode":false,"pivot":{"x":57.83330535888672,"y":17.930221557617189,"z":41.613346099853519},"rotation":{"x":0.1702055037021637,"y":-0.5584218502044678,"z":0.11832898110151291,"w":0.803242564201355},"size":10.474440574645996,"orthographic":false}